LICENSE
MANIFEST.in
README.md
setup.py
OASYS1_PaNOSC.egg-info/PKG-INFO
OASYS1_PaNOSC.egg-info/SOURCES.txt
OASYS1_PaNOSC.egg-info/dependency_links.txt
OASYS1_PaNOSC.egg-info/entry_points.txt
OASYS1_PaNOSC.egg-info/namespace_packages.txt
OASYS1_PaNOSC.egg-info/not-zip-safe
OASYS1_PaNOSC.egg-info/requires.txt
OASYS1_PaNOSC.egg-info/top_level.txt
orangecontrib/__init__.py
orangecontrib/panosc/__init__.py
orangecontrib/panosc/menu/__init__.py
orangecontrib/panosc/shadow/__init__.py
orangecontrib/panosc/shadow/util/__init__.py
orangecontrib/panosc/shadow/util/openPMD.py
orangecontrib/panosc/shadow/util/python_script.py
orangecontrib/panosc/shadow/widgets/__init__.py
orangecontrib/panosc/shadow/widgets/extension/__init__.py
orangecontrib/panosc/shadow/widgets/extension/diffr_poly_1.txt
orangecontrib/panosc/shadow/widgets/extension/diffr_poly_2.txt
orangecontrib/panosc/shadow/widgets/extension/ow_beam_file_reader.py
orangecontrib/panosc/shadow/widgets/extension/ow_beam_file_writer.py
orangecontrib/panosc/shadow/widgets/extension/ow_libpyvinyl_python_script.py
orangecontrib/panosc/shadow/widgets/extension/ow_remote_beamline_open.py
orangecontrib/panosc/shadow/widgets/extension/ow_remote_github_downloader.py
orangecontrib/panosc/shadow/widgets/extension/ow_simex_interaction.py
orangecontrib/panosc/shadow/widgets/extension/spectrum.txt
orangecontrib/panosc/shadow/widgets/extension/icons/beam_file_reader.png
orangecontrib/panosc/shadow/widgets/extension/icons/beam_file_writer.png
orangecontrib/panosc/shadow/widgets/extension/icons/esrf.png
orangecontrib/panosc/shadow/widgets/extension/icons/esrf2.png
orangecontrib/panosc/shadow/widgets/extension/icons/eu.png
orangecontrib/panosc/shadow/widgets/extension/icons/github.png
orangecontrib/panosc/shadow/widgets/extension/icons/python_script.png
orangecontrib/panosc/shadow/widgets/extension/icons/remote_beamline_open.png
orangecontrib/panosc/shadow/widgets/extension/icons/simex_interactor.png
orangecontrib/panosc/shadow/widgets/extension/miscellanea/test_first_widget.txt
orangecontrib/panosc/srw/__init__.py
orangecontrib/panosc/srw/util/__init__.py
orangecontrib/panosc/srw/widgets/__init__.py
orangecontrib/panosc/srw/widgets/extension/__init__.py
orangecontrib/panosc/syned/__init__.py
orangecontrib/panosc/syned/util/__init__.py
